{
  "users": [
    {
      "id": 1,
      "name": "Megha"
    },
    {
      "id": 2,
      "name": "Manohar"
    },
    {
      "id": 3,
      "name": "Harshitha"
    },
    {
      "id": 4,
      "name": "Akash"
    },
    {
      "name": "Salvador Volkman",
      "id": 5
    },
    {
      "name": "Candice Cassin",
      "id": 6
    },
    {
      "name": "Mrs. Mae Block",
      "id": 7
    },
    {
      "name": "Javier Beier",
      "id": 8
    },
    {
      "name": "Barbara Torphy",
      "id": 9
    },
    {
      "name": "Guadalupe Bauch",
      "id": 10
    },
    {
      "name": "Naomi Goyette",
      "id": 11
    },
    {
      "name": "Sonya Batz",
      "id": 12
    },
    {
      "name": "Alicia Klein",
      "id": 13
    },
    {
      "name": "Jacob Littel DVM",
      "id": 14
    },
    {
      "name": "Joanna Douglas II",
      "id": 15
    },
    {
      "name": "Delbert Renner",
      "id": 16
    },
    {
      "name": "Kelli Kemmer",
      "id": 17
    },
    {
      "name": "Mrs. Elvira Kris",
      "id": 18
    },
    {
      "name": "Ted Stark",
      "id": 19
    },
    {
      "name": "Ron Connelly Jr.",
      "id": 20
    },
    {
      "name": "Sidney Howe",
      "id": 21
    },
    {
      "name": "Lila Marquardt",
      "id": 22
    },
    {
      "name": "Mrs. Myrtle Mraz II",
      "id": 23
    },
    {
      "name": "Lindsey Paucek",
      "id": 24
    },
    {
      "name": "Erin Krajcik",
      "id": 25
    },
    {
      "name": "Jon Dietrich III",
      "id": 26
    },
    {
      "name": "Margie Beatty",
      "id": 27
    },
    {
      "name": "Marc McLaughlin",
      "id": 28
    },
    {
      "name": "Tyler Jacobi",
      "id": 29
    },
    {
      "name": "Jaime Erdman",
      "id": 30
    }
  ],
  "albums": [],
  "photos": []
}